fluidly_auth-0.1.3-py3.7-nspkg.pth
fluidly/auth/__init__.py
fluidly/auth/jwt.py
fluidly/auth/jwt_requests.py
fluidly/auth/permissions.py
fluidly/auth/py.typed
fluidly/auth/tests.py
fluidly_auth-0.1.3.dist-info/METADATA
fluidly_auth-0.1.3.dist-info/WHEEL
fluidly_auth-0.1.3.dist-info/namespace_packages.txt
fluidly_auth-0.1.3.dist-info/top_level.txt
fluidly_auth-0.1.3.dist-info/RECORD
