Metadata-Version: 2.1
Name: fluidly-auth
Version: 0.1.3
Summary: Authorisation helpers.
Home-page: https://github.com/fluidly/python-shared
Author: Fluidly
Author-email: tech@fluidly.com
License: UNKNOWN
Platform: UNKNOWN
Requires-Python: >=3.6.0
Requires-Dist: google-auth
Requires-Dist: requests
Requires-Dist: fluidly-structlog
